dloc/__init__.py
dloc/api.py
dloc/eval_benchmark.py
dloc/match_file.py
dloc/core/__init__.py
dloc/core/extract_features.py
dloc/core/match_features.py
dloc/core/overlap_features.py
dloc/core/extractors/__init__.py
dloc/core/extractors/aslfeat.py
dloc/core/extractors/contextdesc.py
dloc/core/extractors/d2net.py
dloc/core/extractors/disk.py
dloc/core/extractors/landmark.py
dloc/core/extractors/r2d2.py
dloc/core/extractors/superpoint.py
dloc/core/matchers/__init__.py
dloc/core/matchers/cotr.py
dloc/core/matchers/disk_match.py
dloc/core/matchers/loftr.py
dloc/core/matchers/nearest_neighbor.py
dloc/core/matchers/superglue.py
dloc/core/overlaps/__init__.py
dloc/core/overlaps/sadnet.py
dloc/core/utils/__init__.py
dloc/core/utils/base_model.py
dloc/core/utils/database.py
dloc/core/utils/parsers.py
dloc/core/utils/read_write_model.py
dloc/core/utils/tools.py
dloc/core/utils/utils.py
dloc/core/utils/viz.py
dloc/evaluate/__init__.py
dloc/evaluate/eval_fuchi.py
dloc/evaluate/eval_hpatches.py
dloc/evaluate/eval_imc.py
dloc/evaluate/eval_megadepth.py
dloc/evaluate/dataloader/__init__.py
dloc/evaluate/dataloader/fuchi.py
dloc/evaluate/dataloader/hpatches.py
dloc/evaluate/dataloader/imc.py
dloc/evaluate/dataloader/megadepth.py
dloc/evaluate/dataloader/utils.py
dloc/evaluate/utils/__init__.py
dloc/evaluate/utils/evaluation.py
dloc/evaluate/utils/imc.py
dloc/evaluate/utils/megadepth.py
dloc/evaluate/utils/utils.py
dloc/evaluate/utils/visualization.py
dloc/geometry/__init__.py
dloc/geometry/pose.py
dloc/models/__init__.py
dloc/models/ASLFeat/__init__.py
dloc/models/ASLFeat/datasets/__init__.py
dloc/models/ASLFeat/datasets/aachen.py
dloc/models/ASLFeat/datasets/base_dataset.py
dloc/models/ASLFeat/datasets/eth.py
dloc/models/ASLFeat/datasets/fmbench.py
dloc/models/ASLFeat/datasets/gl3d.py
dloc/models/ASLFeat/datasets/imw2020.py
dloc/models/ASLFeat/datasets/oxford.py
dloc/models/ASLFeat/datasets/tat.py
dloc/models/ASLFeat/datasets/yfcc.py
dloc/models/ASLFeat/models/__init__.py
superMatch-0.0.5.dist-info/METADATA
superMatch-0.0.5.dist-info/WHEEL
superMatch-0.0.5.dist-info/top_level.txt
superMatch-0.0.5.dist-info/RECORD
