Metadata-Version: 2.1
Name: superMatch
Version: 0.0.5
Summary: Local Feature Extractors and Matchers Network Library for PyTorch
Home-page: https://git.woa.com/matching-benchmark/SuperMatch.git
Author: mumuychen
Author-email: mumuychen@tencent.com
License: UNKNOWN
Download-URL: https://git.woa.com/matching-benchmark/SuperMatch.git/archive/0.0.5.tar.gz
Keywords: deep-learningpytorch,image-matching,superpoint-superglue,loftr-cort-aslfeat-r2d2
Platform: UNKNOWN
Requires-Python: >=3.6
Requires-Dist: numpy
Requires-Dist: tqdm
Requires-Dist: scipy
Requires-Dist: opencv-contrib-python
Requires-Dist: h5py
Requires-Dist: kornia
Requires-Dist: pydegensac
